entab-0.3.3.dist-info/METADATA
entab-0.3.3.dist-info/WHEEL
entab/__init__.py
entab/entab.cpython-37m-x86_64-linux-gnu.so
entab-0.3.3.dist-info/RECORD
