Metadata-Version: 2.3
Name: entab
Version: 0.3.3
Summary: Record-format file reader
Author: Roderick <rbovee@gmail.com>
Author-email: Roderick <rbovee@gmail.com>
License: MIT
Project-URL: Source Code, https://github.com/bovee/entab
